ebenv/__init__.py
ebenv/_compat.py
ebenv-0.3.1.dist-info/LICENSE
ebenv-0.3.1.dist-info/METADATA
ebenv-0.3.1.dist-info/WHEEL
ebenv-0.3.1.dist-info/entry_points.txt
ebenv-0.3.1.dist-info/top_level.txt
ebenv-0.3.1.dist-info/RECORD
