Metadata-Version: 2.1
Name: ebenv
Version: 0.3.1
Summary: AWS Elastic Beanstalk environment dumper/extractor.
Home-page: https://github.com/steinnes/ebenv
Author: Steinn Eldjarn Sigurdarson
Author-email: steinnes@gmail.com
License: UNKNOWN
Keywords: aws,elasticbeanstalk,environment
Platform: UNKNOWN
Requires-Dist: boto3 (>=1.2.3)
Requires-Dist: click (==6.2)
